esv_sdk/__init__.py
esv_sdk/_hooks/__init__.py
esv_sdk/_hooks/custom/prefixapikey.py
esv_sdk/_hooks/registration.py
esv_sdk/_hooks/sdkhooks.py
esv_sdk/_hooks/types.py
esv_sdk/_version.py
esv_sdk/basesdk.py
esv_sdk/httpclient.py
esv_sdk/models/__init__.py
esv_sdk/models/apierror.py
esv_sdk/models/error.py
esv_sdk/models/getpassageaudioop.py
esv_sdk/models/getpassagehtmlop.py
esv_sdk/models/getpassagetextop.py
esv_sdk/models/passagemeta.py
esv_sdk/models/passageresponse.py
esv_sdk/models/searchpassagesop.py
esv_sdk/models/security.py
esv_sdk/passages.py
esv_sdk/py.typed
esv_sdk/sdk.py
esv_sdk/sdkconfiguration.py
esv_sdk/types/__init__.py
esv_sdk/types/basemodel.py
esv_sdk/utils/__init__.py
esv_sdk/utils/annotations.py
esv_sdk/utils/datetimes.py
esv_sdk/utils/enums.py
esv_sdk/utils/eventstreaming.py
esv_sdk/utils/forms.py
esv_sdk/utils/headers.py
esv_sdk/utils/logger.py
esv_sdk/utils/metadata.py
esv_sdk/utils/queryparams.py
esv_sdk/utils/requestbodies.py
esv_sdk/utils/retries.py
esv_sdk/utils/security.py
esv_sdk/utils/serializers.py
esv_sdk/utils/url.py
esv_sdk/utils/values.py
esv_sdk-0.4.0.dist-info/LICENSE
esv_sdk-0.4.0.dist-info/METADATA
esv_sdk-0.4.0.dist-info/WHEEL
esv_sdk-0.4.0.dist-info/RECORD
