Metadata-Version: 2.3
Name: esv-sdk
Version: 0.4.0
Summary: Python Client SDK Generated by Speakeasy.
Author: Walker Lockard
Requires-Python: >=3.9.2
Classifier: Programming Language :: Python :: 3
Classifier: Programming Language :: Python :: 3.10
Classifier: Programming Language :: Python :: 3.11
Classifier: Programming Language :: Python :: 3.12
Classifier: Programming Language :: Python :: 3.13
Requires-Dist: httpx (>=0.28.1)
Requires-Dist: jsonpath-python (>=1.0.6)
Requires-Dist: pydantic (>=2.11.2)
Project-URL: Repository, https://github.com/walker-tx/esv-sdk-py.git
